wisex/__init__.py
wisex/_version.py
wisex/wisex.py
wisex/metrics/fosterboys.py
wisex/optimizers/basin.py
wisex/optimizers/jacobi.py
wisex-0.0.1.dist-info/METADATA
wisex-0.0.1.dist-info/WHEEL
wisex-0.0.1.dist-info/top_level.txt
wisex-0.0.1.dist-info/RECORD
