Metadata-Version: 2.4
Name: wisex
Version: 0.0.1
Summary: wisex
Home-page: https://www.github.com/ifilot/wisex
Author: Ivo Filot
Author-email: Ivo Filot <i.a.w.filot@tue.nl>
Maintainer-email: Ivo Filot <i.a.w.filot@tue.nl>
License: GPL-3.0-or-later
Project-URL: Homepage, https://www.github.com/ifilot/wisex
Project-URL: Bug Tracker, https://www.github.com/ifilot/wisex/issues
Classifier: Programming Language :: Python :: 3
Classifier: Operating System :: OS Independent
Requires-Python: >=3.5
Requires-Dist: scipy
Requires-Dist: numpy
Dynamic: author
Dynamic: home-page
Dynamic: requires-python
